Metadata-Version: 2.1
Name: geneparse
Version: 0.8.2
Summary: A suite of parse for genotype formats.
Home-page: https://github.com/pgxcentre/geneparse
License: MIT
Keywords: bioinformatics genetics statistics
Classifier: Development Status :: 4 - Beta
Classifier: Intended Audience :: Science/Research
Classifier: License :: Free for non-commercial use
Classifier: Operating System :: Unix
Classifier: Operating System :: POSIX :: Linux
Classifier: Operating System :: MacOS :: MacOS X
Classifier: Operating System :: Microsoft
Classifier: Programming Language :: Python
Classifier: Programming Language :: Python :: 3.4
Classifier: Programming Language :: Python :: 3.5
Classifier: Programming Language :: Python :: 3.6
Classifier: Topic :: Scientific/Engineering :: Bio-Informatics
License-File: LICENSE
Requires-Dist: numpy (>=1.11.0)
Requires-Dist: pandas (>=0.19.0)
Requires-Dist: pyplink (>=1.3.4)
Requires-Dist: setuptools (>=26.1.0)
Requires-Dist: biopython (>=1.68)
Requires-Dist: pybgen (>=0.7.0)
